Metadata-Version: 2.1
Name: colortextprint
Version: 0.1
Summary: Print colored text on console in python
Home-page: UNKNOWN
Author: Prathamesh Sable
Author-email: prathameshks2003@gmail.com
License: UNKNOWN
Keywords: python,colortext,color,console,print_color
Platform: UNKNOWN
Classifier: Development Status :: 1 - Planning
Classifier: Intended Audience :: Developers
Classifier: Programming Language :: Python :: 3
Classifier: Operating System :: Unix
Classifier: Operating System :: MacOS :: MacOS X
Classifier: Operating System :: Microsoft :: Windows
